[
    {
        "model": "dubsapi.product",
        "pk": 1,
        "fields": {
            "name": "The Classic",
            "price": 10.00,
            "description": "Mustard, Mayo, Lettuce, Onion, Tomato, Cheddar",
            "image_path": "https://dubs-doubles.herokuapp.com/media/products/ad50b196-f596-4890-9df2-c42ab5bb4443.jpg",
            "product_type_id": 1,
            "quantity": 0
        }
    },
    {
        "model": "dubsapi.product",
        "pk": 2,
        "fields": {
            "name": "The Rodeo",
            "price": 10.00,
            "description": "Mustard, Mayo, Onion, Pickle, American Cheese, Wrapped in Foil",
            "image_path": "https://dubs-doubles.herokuapp.com/media/products/9331f6a1-b678-452e-a65a-c3cecde89f6c.jpg",
            "product_type_id": 1,
            "quantity": 0
        }
    },
    {
        "model": "dubsapi.product",
        "pk": 3,
        "fields": {
            "name": "The Stranger",
            "price": 10.00,
            "description": "Hatch Chilis, American Cheese, Gifford's Bacon",
            "image_path": "https://dubs-doubles.herokuapp.com/media/products/965a93d9-a8d7-42c3-b491-03e888e1a6bf.jpg",
            "product_type_id": 1,
            "quantity": 0
        }
    },
    {
        "model": "dubsapi.product",
        "pk": 4,
        "fields": {
            "name": "The Beyond",
            "price": 12.00,
            "description": "Mustard, Mayo, Diced Onion, Pickles, Cheddar",
            "image_path": "https://dubs-doubles.herokuapp.com/media/products/9ba3a99d-c47f-4edf-8f07-4b350724af1a.jpg",
            "product_type_id": 1,
            "quantity": 0
        }
    },
    {
        "model": "dubsapi.product",
        "pk": 5,
        "fields": {
            "name": "The Main Street",
            "price": 10.00,
            "description": "Mustard, Onion, Pickle, Benton's Bacon, Cheddar",
            "image_path": "https://dubs-doubles.herokuapp.com/media/products/ebc13c0f-bcb0-472a-97cd-afa0ab5b8b2a.jpg",
            "product_type_id": 1,
            "quantity": 0
        }
    },
    {
        "model": "dubsapi.product",
        "pk": 6,
        "fields": {
            "name": "Crinkle Cut Fries",
            "price": 3.00,
            "description": "",
            "image_path": "https://dubs-doubles.herokuapp.com/media/products/c1801d9c-5ab0-4153-aebc-9459684e8098.jpg",
            "product_type_id": 2,
            "quantity": 0
        }
    },
    {
        "model": "dubsapi.product",
        "pk": 7,
        "fields": {
            "name": "Tater Tots",
            "price": 3.00,
            "description": "",
            "image_path": "https://dubs-doubles.herokuapp.com/media/products/d3b9e7dd-8de6-4af3-ac8c-9932ddfc577c.jpg",
            "product_type_id": 2,
            "quantity": 0
        }
    },
    {
        "model": "dubsapi.product",
        "pk": 8,
        "fields": {
            "name": "Onion Rings",
            "price": 4.50,
            "description": "",
            "image_path": "https://dubs-doubles.herokuapp.com/media/products/00122b9d-fec7-4504-b4fa-d63a59ff22d9.jpg",
            "product_type_id": 2,
            "quantity": 0
        }
    },
    {
        "model": "dubsapi.product",
        "pk": 9,
        "fields": {
            "name": "The BYOBurger",
            "price": 0.00,
            "description": "Build Your Own Burger",
            "image_path": "https://dubs-doubles.herokuapp.com/media/products/e1a93f4d-b226-48ab-abed-5c339d302f1c.jpg",
            "product_type_id": 1,
            "quantity": 0
        }
    },
    {
        "model": "dubsapi.product",
        "pk": 10,
        "fields": {
            "name": "Curly Fries",
            "price": 3.00,
            "description": "",
            "image_path": "https://dubs-doubles.herokuapp.com/media/products/95c70e05-45f9-41a5-87ba-2fe1e55edde5.jpg",
            "product_type_id": 2,
            "quantity": 0
        }
    }
]